pgsql_utils/__init__.py
pgsql_utils/postgresql_utils.py
pgsql_utils-1.0.5.dist-info/licenses/LICENSE
pgsql_utils-1.0.5.dist-info/METADATA
pgsql_utils-1.0.5.dist-info/WHEEL
pgsql_utils-1.0.5.dist-info/top_level.txt
pgsql_utils-1.0.5.dist-info/RECORD
