Metadata-Version: 2.4
Name: pgsql-utils
Version: 1.0.5
Summary: 一个用于简化PostgreSQL数据库操作的Python工具包
Author-email: 苏寅 <suyin_long@163.com>
License: Apache-2.0
Project-URL: Homepage, https://gitee.com/suyin-long/pgsql-utils
Project-URL: Bug Reports, https://gitee.com/suyin-long/pgsql-utils/issues
Project-URL: Source, https://gitee.com/suyin-long/pgsql-utils
Classifier: Development Status :: 4 - Beta
Classifier: Intended Audience :: Developers
Classifier: License :: OSI Approved :: Apache Software License
Classifier: Operating System :: OS Independent
Classifier: Programming Language :: Python :: 3
Classifier: Programming Language :: Python :: 3.7
Classifier: Programming Language :: Python :: 3.8
Classifier: Programming Language :: Python :: 3.9
Classifier: Programming Language :: Python :: 3.10
Classifier: Programming Language :: Python :: 3.11
Requires-Python: >=3.7
License-File: LICENSE
Requires-Dist: psycopg2>=2.9.10
Requires-Dist: colorPrintConsole>=1.0.8
Provides-Extra: dev
Requires-Dist: pytest>=6.0; extra == "dev"
Requires-Dist: black; extra == "dev"
Requires-Dist: flake8; extra == "dev"
Dynamic: license-file
